evalidator/__init__.py
evalidator/evalidator.py
evalidator-0.1.4.dist-info/DESCRIPTION.rst
evalidator-0.1.4.dist-info/METADATA
evalidator-0.1.4.dist-info/RECORD
evalidator-0.1.4.dist-info/WHEEL
evalidator-0.1.4.dist-info/entry_points.txt
evalidator-0.1.4.dist-info/metadata.json
evalidator-0.1.4.dist-info/top_level.txt
