Metadata-Version: 2.0
Name: evalidator
Version: 0.1.4
Summary: Checks if an e-mail address exists or not
Home-page: https://www.github.com/ritiek/email-validator
Author: Ritiek Malhotra
Author-email: ritiekmalhotra123@gmail.com
License: MIT
Download-URL: https://github.com/ritiek/email-validator/archive/v0.1.4.tar.gz
Keywords: email,validator,exists,check,command-line,library,python
Platform: UNKNOWN
Requires-Dist: requests
